{"stats":{"minecraft:mined":{"minecraft:podzol":2,"minecraft:oak_sapling":2,"minecraft:iron_ore":1,"minecraft:birch_log":3,"minecraft:andesite":3,"minecraft:granite":4,"minecraft:grass_block":37,"minecraft:coal_ore":1,"minecraft:oak_log":7,"minecraft:chest":2,"minecraft:gravel":5,"minecraft:dirt":22,"minecraft:stone":32,"minecraft:oak_planks":8,"minecraft:diorite":4},"minecraft:broken":{"minecraft:wooden_axe":1,"minecraft:wooden_shovel":1},"minecraft:picked_up":{"minecraft:birch_log":2,"minecraft:feather":3,"minecraft:andesite":6,"minecraft:oak_fence":1,"minecraft:brown_mushroom":2,"minecraft:wooden_pickaxe":1,"minecraft:red_mushroom":2,"minecraft:gravel":7,"minecraft:oak_log":9,"minecraft:diorite":4,"minecraft:dirt":62,"silentgear:sinew":1,"botania:pebble":2,"minecraft:rotten_flesh":1,"minecraft:wheat_seeds":3,"ars_nouveau:worn_notebook":1,"minecraft:granite":4,"minecraft:iron_ore":1,"minecraft:wooden_shovel":1,"minecraft:oak_sapling":3,"minecraft:melon_slice":4,"minecraft:chest":2,"minecraft:coal":4,"minecraft:oak_planks":5,"minecraft:cobblestone":45,"minecraft:egg":1},"minecraft:crafted":{"minecraft:stick":16,"minecraft:stone_pickaxe":1,"minecraft:wooden_axe":1,"minecraft:birch_planks":4,"minecraft:air":87},"minecraft:killed":{"minecraft:zombie":1},"minecraft:custom":{"minecraft:time_since_rest":361,"minecraft:sprint_one_cm":3335,"minecraft:damage_taken":5509,"minecraft:walk_one_cm":54048,"minecraft:mob_kills":2,"minecraft:drop":14,"minecraft:damage_dealt":2021,"minecraft:interact_with_crafting_table":9,"minecraft:fly_one_cm":9380,"minecraft:player_kills":17,"minecraft:open_chest":21,"minecraft:play_one_minute":54992,"minecraft:crouch_one_cm":6716,"minecraft:deaths":16,"minecraft:sneak_time":3082,"minecraft:jump":174,"minecraft:leave_game":1,"minecraft:time_since_death":333,"minecraft:damage_resisted":14,"minecraft:fall_one_cm":1637708},"minecraft:dropped":{"minecraft:dirt":5,"botania:pebble":1,"minecraft:wooden_shovel":1,"minecraft:oak_fence":7},"minecraft:killed_by":{"minecraft:player":11},"minecraft:used":{"minecraft:oak_fence":7,"minecraft:wooden_axe":32,"minecraft:stone_pickaxe":45,"minecraft:oak_planks":25,"minecraft:wooden_pickaxe":23,"minecraft:wooden_shovel":58,"minecraft:gravel":1,"minecraft:dirt":37,"minecraft:oak_sapling":2}},"DataVersion":2586}